fds/__init__.py
fds/sdk/__init__.py
fds/sdk/FactSetContentAPIBatch/__init__.py
fds/sdk/FactSetContentAPIBatch/api_client.py
fds/sdk/FactSetContentAPIBatch/configuration.py
fds/sdk/FactSetContentAPIBatch/exceptions.py
fds/sdk/FactSetContentAPIBatch/model_utils.py
fds/sdk/FactSetContentAPIBatch/rest.py
fds/sdk/FactSetContentAPIBatch/api/__init__.py
fds/sdk/FactSetContentAPIBatch/api/batch_processing_api.py
fds/sdk/FactSetContentAPIBatch/apis/__init__.py
fds/sdk/FactSetContentAPIBatch/model/__init__.py
fds/sdk/FactSetContentAPIBatch/model/batch_data_request.py
fds/sdk/FactSetContentAPIBatch/model/batch_data_response.py
fds/sdk/FactSetContentAPIBatch/model/batch_status.py
fds/sdk/FactSetContentAPIBatch/model/batch_status_request.py
fds/sdk/FactSetContentAPIBatch/model/batch_status_response.py
fds/sdk/FactSetContentAPIBatch/model/error_response.py
fds/sdk/FactSetContentAPIBatch/model/error_response_sub_errors.py
fds/sdk/FactSetContentAPIBatch/models/__init__.py
fds.sdk.FactSetContentAPIBatch-0.21.14.dist-info/LICENSE
fds.sdk.FactSetContentAPIBatch-0.21.14.dist-info/METADATA
fds.sdk.FactSetContentAPIBatch-0.21.14.dist-info/WHEEL
fds.sdk.FactSetContentAPIBatch-0.21.14.dist-info/top_level.txt
fds.sdk.FactSetContentAPIBatch-0.21.14.dist-info/RECORD
